agentauth/__init__.py
agentauth/agentauth.py
agentauth/credential.py
agentauth/credential_manager.py
agentauth/email_service.py
agentauth/id_generator.py
agentauth/py.typed
agentauth-0.4.0.dist-info/METADATA
agentauth-0.4.0.dist-info/WHEEL
agentauth-0.4.0.dist-info/licenses/LICENSE.txt
agentauth-0.4.0.dist-info/RECORD
