Metadata-Version: 2.4
Name: agentauth
Version: 0.4.0
Summary: Automated authentication for web agents
Author: Cole Hecht
License-File: LICENSE.txt
Requires-Python: >=3.11
Requires-Dist: browser-use>=0.1.36
Requires-Dist: browserbase>=1.1.0
Requires-Dist: imap-tools>=1.10.0
Requires-Dist: langchain>=0.1.0
Requires-Dist: onepassword-sdk>=0.1.7
Requires-Dist: pyotp>=2.9.0
Requires-Dist: python-dotenv>=1.0.1
Requires-Dist: structlog>=25.1.0
